ltoolx/__init__.py
ltoolx/gurobi_utils.py
ltoolx/matplotlib_utils.py
ltoolx/svg_utils.py
ltoolx-0.1.5.dist-info/METADATA
ltoolx-0.1.5.dist-info/WHEEL
ltoolx-0.1.5.dist-info/licenses/LICENSE
ltoolx-0.1.5.dist-info/RECORD
