Metadata-Version: 2.4
Name: ltoolx
Version: 0.1.5
Summary: Common tool packaging
Project-URL: Homepage, https://github.com/jchliao/ltoolx
Project-URL: Repository, https://github.com/jchliao/ltoolx
Author: jchl, riverflows2333
License: Copyright (c) 2018 The Python Packaging Authority
License-File: LICENSE
Requires-Python: >=3.12
Requires-Dist: beautifulsoup4
Requires-Dist: gurobipy
Requires-Dist: ipython
Requires-Dist: lxml
Requires-Dist: matplotlib
Requires-Dist: matplotlib-inline
Requires-Dist: numpy
Requires-Dist: pywin32; sys_platform == 'win32'
